nightshift/__init__.py
nightshift/__main__.py
nightshift/bmrb.py
nightshift/cli.py
nightshift/constants.py
nightshift/nightshift.py
nightshift/plotting.py
nightshift/selector.py
nightshift-1.0.1.dist-info/LICENSE
nightshift-1.0.1.dist-info/METADATA
nightshift-1.0.1.dist-info/WHEEL
nightshift-1.0.1.dist-info/entry_points.txt
nightshift-1.0.1.dist-info/top_level.txt
nightshift-1.0.1.dist-info/RECORD
