Metadata-Version: 2.1
Name: nightshift
Version: 1.0.1
Summary: A python library and command line program for plotting simulated 2D and 3D NMR spectra from assigned chemical shifts from the BMRB
Home-page: https://github.com/ianfucci/nightshift
Author: Ian Fucci
Author-email: fucci.ian@gmail.com
License: UNKNOWN
Keywords: nmr,chemical shift,bmrb,plotting
Platform: UNKNOWN
Classifier: Intended Audience :: Science/Research
Classifier: License :: OSI Approved :: MIT License
Classifier: Programming Language :: Python :: 3
Requires-Python: >=3.6
License-File: LICENSE
Requires-Dist: requests
Requires-Dist: matplotlib
Requires-Dist: pyqt5
